tom_swe/__init__.py
tom_swe/logging_config.py
tom_swe/py.typed
tom_swe/rag_module.py
tom_swe/tom_agent.py
tom_swe/tom_module.py
tom_swe/utils.py
tom_swe/generation/__init__.py
tom_swe/generation/action.py
tom_swe/generation/dataclass.py
tom_swe/generation/generate.py
tom_swe/generation/output_parsers.py
tom_swe/memory/__init__.py
tom_swe/memory/conversation_processor.py
tom_swe/memory/local.py
tom_swe/memory/locations.py
tom_swe/memory/store.py
tom_swe/prompts/__init__.py
tom_swe/prompts/manager.py
tom_swe/prompts/templates/give_suggestions.jinja2
tom_swe/prompts/templates/message_condensation.jinja2
tom_swe/prompts/templates/session_analysis.jinja2
tom_swe/prompts/templates/sleeptime_compute.jinja2
tom_swe/prompts/templates/user_analysis.jinja2
tom_swe-1.0.1.dist-info/METADATA
tom_swe-1.0.1.dist-info/WHEEL
tom_swe-1.0.1.dist-info/RECORD
