Metadata-Version: 2.4
Name: tom-swe
Version: 1.0.1
Summary: Theory of Mind modeling for Software Engineering assistants
Project-URL: Homepage, https://github.com/All-Hands-AI/ToM-SWE
Project-URL: Repository, https://github.com/All-Hands-AI/ToM-SWE
Project-URL: Issues, https://github.com/All-Hands-AI/ToM-SWE/issues
Project-URL: Documentation, https://github.com/All-Hands-AI/ToM-SWE#readme
Author: Research Team
License: MIT
Keywords: ai-assistant,llm,psychology,rag,software-engineering,theory-of-mind,user-modeling
Classifier: Development Status :: 4 - Beta
Classifier: Intended Audience :: Developers
Classifier: Intended Audience :: Science/Research
Classifier: License :: OSI Approved :: MIT License
Classifier: Operating System :: OS Independent
Classifier: Programming Language :: Python :: 3
Classifier: Programming Language :: Python :: 3.10
Classifier: Programming Language :: Python :: 3.11
Classifier: Programming Language :: Python :: 3.12
Classifier: Topic :: Scientific/Engineering :: Artificial Intelligence
Classifier: Topic :: Software Development :: Libraries :: Python Modules
Requires-Python: >=3.10
Requires-Dist: aiofiles>=23.0.0
Requires-Dist: bm25s>=0.2.0
Requires-Dist: datasets>=2.0.0
Requires-Dist: fastapi>=0.104.0
Requires-Dist: httpx>=0.25.0
Requires-Dist: huggingface-hub>=0.0.0
Requires-Dist: jinja2>=3.0.0
Requires-Dist: json-repair>=0.1.0
Requires-Dist: litellm>=1.0.0
Requires-Dist: numpy>=1.24.0
Requires-Dist: pandas>=2.0.0
Requires-Dist: pydantic>=2.0.0
Requires-Dist: pystemmer>=2.2.0
Requires-Dist: python-dotenv>=1.0.0
Requires-Dist: rich>=13.0.0
Requires-Dist: tiktoken>=0.8.0
Requires-Dist: tqdm>=4.65.0
Requires-Dist: typing-extensions>=4.0.0
Requires-Dist: uvicorn>=0.24.0
Provides-Extra: dev
Requires-Dist: black>=22.0.0; extra == 'dev'
Requires-Dist: isort>=5.0.0; extra == 'dev'
Requires-Dist: mypy>=1.0.0; extra == 'dev'
Requires-Dist: pre-commit>=3.6.0; extra == 'dev'
Requires-Dist: pytest-cov>=6.2.1; extra == 'dev'
Requires-Dist: pytest>=7.0.0; extra == 'dev'
Requires-Dist: ruff>=0.3.0; extra == 'dev'
